whatsapp_trend_plotter/__init__.py
whatsapp_trend_plotter/__main__.py
whatsapp_trend_plotter/terminal_formatting.py
whatsapp_trend_plotter/version.py
whatsapp_trend_plotter-2026.1.1.dist-info/METADATA
whatsapp_trend_plotter-2026.1.1.dist-info/WHEEL
whatsapp_trend_plotter-2026.1.1.dist-info/entry_points.txt
whatsapp_trend_plotter-2026.1.1.dist-info/licenses/LICENSE.txt
whatsapp_trend_plotter-2026.1.1.dist-info/RECORD
