Metadata-Version: 2.4
Name: whatsapp-trend-plotter
Version: 2026.1.1
Summary: I was interested when people were washing their laundry in my apartment complex. This matches a regex against an exported whatsapp chat to produce an overview of matches over time.
Author-email: Guenthner <guenthner.jonathan@gmail.com>
License-File: LICENSE.txt
Classifier: License :: OSI Approved :: MIT License
Classifier: Operating System :: OS Independent
Classifier: Programming Language :: Python :: 3
Requires-Python: >=3.8
